build/lib/docs/conf.py
build/lib/pulse_deadtime_fix/__init__.py
build/lib/pulse_deadtime_fix/_version.py
build/lib/pulse_deadtime_fix/core.py
build/lib/pulse_deadtime_fix/simulate.py
build/lib/pulse_deadtime_fix/version.py
build/lib/pulse_deadtime_fix/tests/__init__.py
build/lib/pulse_deadtime_fix/tests/test_core.py
build/lib/pulse_deadtime_fix/tests/test_simulate.py
docs/Makefile
docs/conf.py
docs/index.rst
docs/make.bat
docs/images/crab_deadtime_corr.jpg
docs/images/simulate_corr.jpg
licenses/LICENSE.rst
licenses/README.rst
licenses/TEMPLATE_LICENSE.rst
pulse_deadtime_fix/__init__.py
pulse_deadtime_fix/_version.py
pulse_deadtime_fix/core.py
pulse_deadtime_fix/simulate.py
pulse_deadtime_fix/version.py
pulse_deadtime_fix/data/README.rst
pulse_deadtime_fix/tests/__init__.py
pulse_deadtime_fix/tests/test_core.py
pulse_deadtime_fix/tests/test_simulate.py
pulse_deadtime_fix-0.1.dist-info/METADATA
pulse_deadtime_fix-0.1.dist-info/WHEEL
pulse_deadtime_fix-0.1.dist-info/top_level.txt
pulse_deadtime_fix-0.1.dist-info/RECORD
