Metadata-Version: 2.1
Name: pulse_deadtime_fix
Version: 0.1
Summary: Fix dead time distortion of pulse profiles
Author-email: Matteo B <matteo@matteobachetti.it>
License: Copyright (c) 2024, Matteo B
Project-URL: repository, https://github.com/matteobachetti/pulse_deadtime_fix
Requires-Python: >=3.9
Requires-Dist: numpy
Requires-Dist: astropy
Requires-Dist: stingray
Requires-Dist: numba
Provides-Extra: docs
Requires-Dist: sphinx ; extra == 'docs'
Requires-Dist: sphinx-automodapi ; extra == 'docs'
Provides-Extra: test
Requires-Dist: pytest ; extra == 'test'
Requires-Dist: pytest-doctestplus ; extra == 'test'
Requires-Dist: pytest-cov ; extra == 'test'
